<?xml version="1.0" encoding="UTF-8"?>
<carreras>
    <carrera cve_carrera="40" cve_division="12" nombre="Ingeniería en Gestión de Proyectos" icono="img/movil/android/oferta_educativa/gestion de proyectos.png" img="img/divisiones/carreras/portada_ing_gestion_proyectos.png" url="http://www.uttab.edu.mx/oferta_educativa/agep/ingenieria_gestion_proyectos.action">
        <informacion_extra><![CDATA[
<ul style="list-style-image: url('http://www.uttab.edu.mx/img/divisiones/carreras/people.png');">
<li><h4>Tener gusto por:</h4>
<ul style="list-style-image: url('img/lista.png');">
<li>Administrar proyectos</li>
<li>Tener tu propia empresa</li>
<li>Administrar una empresa</li>
<li>El manejo de personal</li>
<li>La investigación</li>
</ul>
</li>
</ul>
<ul style="list-style-image: url('http://www.uttab.edu.mx/img/divisiones/carreras/maletin.png');">
<li><h4>¿Dónde podrá trabajar?</h4>
<ul style="list-style-image: url('img/lista.png');">
<li>En la administración de empresas públicas y privadas</li>
<li>En tu propia empresa</li>
<li>En el sector público o privado como gerente o director de proyectos</li>
<li>Como líder o gestor en procesos de planeación estratégica</li>
<li>Cómo consultor evaluando proyectos</li>
</ul>
</li>
</ul>
<ul>
<li><h4>¿Qué aprenderá durante la carrera?</h4>
<ul style="list-style-image: url('img/lista.png');">
<li>Gestionar el financiamiento y la ejecución de proyectos de inversión</li>
<li>Aplicar la normatividad y reglas de operación en organismos e instituciones</li>
<li>Formular y ejecutar planes para la creación y/o expansión de empresas</li>
<li>Dirigir los procesos de consultoría financiera, mercadotecnia y reingeniería</li>
<li>Dirigir la planeación estratégica para la toma de decisiones</li>
</ul>
</li>
</ul> 
]]>
        </informacion_extra>
    </carrera>
    <carrera cve_carrera="39" cve_division="12" nombre="TSU en Administración Área Administración y Evaluación de Proyectos" continuidad="40"></carrera>
    <carrera cve_carrera="61" cve_division="12" nombre="Ingeniería en Desarrollo e Innovación Empresarial" icono="img/movil/android/oferta_educativa/desarrollo_innovacion_empresarial.png" img="img/divisiones/carreras/portada_ing_desarrollo_innovacion_empresarial.png" url="http://www.uttab.edu.mx/oferta_educativa/agep/ingenieria_desarrollo_innovacion_empresarial.action">
        <informacion_extra><![CDATA[
<ul style="list-style-image: url('http://www.uttab.edu.mx/img/divisiones/carreras/people.png');">
<li><h4>Tener gusto por:</h4>
<ul style="list-style-image: url('img/lista.png');">
<li>La optimización de procesos administrativos con enfoque en comercialización</li>
<li>Proyección de una empresa en términos de mercadotecnia</li>
<li>Utilización de herramientas administrativas para la mejora continua</li>
<li>Manejo de personal con enfoque en ventas</li>
<li>Toma de decisiones asertivas para el desarrollo de un negocio</li>
</ul>
</li>
</ul>
<ul style="list-style-image: url('http://www.uttab.edu.mx/img/divisiones/carreras/maletin.png');">
<li><h4>¿Dónde podrá trabajar?</h4>
<ul style="list-style-image: url('img/lista.png');">
<li>Empresas del sector industrial</li>
<li>Empresas de comercialización</li>
<li>Organismos financieros</li>
<li>Agencias de publicidad e investigación de mercado</li>
<li>Tu propia empresa</li>
</ul>
</li>
</ul>
<ul>
<li><h4>¿Qué aprenderá durante la carrera?</h4>
<ul style="list-style-image: url('img/lista.png');">
<li>Ejecutar estrategias de capital humano para el cumplimiento de los objetivos</li>
<li>Diseñar planes financieros para el crecimiento de la organización</li>
<li>Diseñar procesos administrativos para la eficiencia y eficacia organizacional</li>
<li>Diseñar planes comerciales para potenciar la competitividad de la empresa</li>
<li>Incrementar las utilidades diseñando y ejecutando procesos de compra y venta</li>
</ul>
</li>
</ul> 
]]>
        </informacion_extra>
    </carrera>
    <carrera cve_carrera="58" cve_division="12" nombre="TSU en Desarrollo de Negocios Área Mercadotecnia" continuidad="61"></carrera>
    <carrera cve_carrera="9" cve_division="12" nombre="TSU en Contaduría" tipo="2" icono="img/movil/android/oferta_educativa/tsu_contaduria.png" img="img/divisiones/carreras/portada_tsu_contaduria.png" url="http://www.uttab.edu.mx/oferta_educativa/agep/tsu_contaduria.action">
        <informacion_extra>
<![CDATA[  
<ul style="list-style-image: url('img/lista.png');">
            <li><h4>¿Tienes interés o gusto por?</h4>
                <ul>
                    <li>Habilidades de gestión de la información</li>
                    <li>Capacidad de análisis y síntesis</li>
                    <li>Resolución de problemas</li>
                    <li>Toma de decisiones </li>
                    <li>Manejo de negocios</li>
                    <li>Autoaprendizaje</li>
                </ul>
            </li>
        </ul>
        <ul style="list-style-image: url('img/lista.png');">
            <li><h4>¿En dónde podré trabajar?</h4>
                <ul>
                    <li>Coordinador de áreas contables, financiera o fiscal.</li> 
                    <li>Servicios profesionales  (asesorías contable, financiera o fiscal)</li> 
                    <li>Empresas públicas y privadas</li> 
                    <li>Dependencias públicas federales, estatales y municipales</li> 
                    <li>Coordinador de administración de personal</li> 
                </ul>
            </li>
        </ul>
        <ul style="list-style-image: url('img/lista.png');">
            <li><h4>Qué aprenderé durante la carrera?</h4>
                <ul>
                    <li>Realizar estados financieros conforme a las NIF’s</li>
                    <li>Diagnosticar y evaluar la situación financiera de una entidad</li>
                    <li>Gestionar los trámites administrativos de acuerdo al marco jurídico de la entidad</li>
                    <li>Realizar los trámites necesarios para cumplir las disposiciones vigentes</li>
                    <li>Formular informes financieros para la toma de decisiones</li>
                    <li>Interpretación y cálculos de las obligaciones fiscales de personas físicas y morales</li>
                    <li>Tratamiento contable del RIF (Régimen de Incorporación Fiscal)</li>
                </ul>
            </li>
        </ul> 
]]>
        </informacion_extra>
    </carrera>
    <carrera cve_carrera="42" cve_division="13" nombre="Ingeniería en Procesos Bioalimentarios" icono="img/movil/android/oferta_educativa/bioalimentario.png" img="img/divisiones/carreras/portada_ing_procesos_bioalimentarios.png" url="http://www.uttab.edu.mx/oferta_educativa/procesos/ingenieria_procesos_bioalimentarios.action">
        <informacion_extra><![CDATA[                                         <ul style="list-style-image: url('img/lista.png');">
                        <li><h4>¿Quién es el Ingeniero en Procesos Bioalimentarios?</h4>
                            <ul class="list-unstyled">
                                <li>
                                    <p> Es un profesionista con conocimientos científicos y 
										tecnológicos capacitado para resolver las 
										problemáticas actuales de la industria alimentaria.
  									</p>
                                </li>
							</ul>
                        </li>
                    </ul>
                    <ul style="list-style-image: url('img/lista.png');">
                        <li><h4>¿Qué aprenderá durante la carrera?</h4>
                            <ul class="list-unstyled">
                                <li> 
									<p>	A realizar e interpretar análisis fisicoquímicos, 
										microbiológicos, sensoriales y nutrimentales, 
										competente para elaborar nuevos productos 
										alimentarios aprovechando los recursos de la región y 
										para operar maquinarias utilizadas en la industria 
										alimentaria. Así como todo lo relacionado con las 
										certificaciones en sistemas de calidad alimentaria y 
										manejo higiénico de los alimentos.
									</p>
								</li>
                            </ul>
                        </li>
                    </ul>
                    <ul style="list-style-image: url('img/lista.png');">
                        <li><h4>¿En dónde podrá trabajar?</h4>
                            <ul  class="list-unstyled">
                                <li><p>	En las diferentes áreas de las empresas públicas o 
										privadas relacionadas con la industria alimentaria, 
										tales como: laboratorios de análisis de los alimentos, 
										líneas de producción de alimentos, consultoría sobre 
										los sistemas de calidad alimentaria de los productos 
										agroalimentarios, desarrollo de investigación de 
										nuevos productos y en la creación de su propia 
										empresa.
									</p>
								</li>
                            </ul>
                        </li>
                    </ul> ]]></informacion_extra>
    </carrera>
    <carrera cve_carrera="47" cve_division="13" nombre="TSU en Procesos Alimentarios" continuidad="42"></carrera>
    <carrera cve_carrera="51" cve_division="13" nombre="Ingeniería en Mantenimiento Industrial" icono="img/movil/android/oferta_educativa/mantenimiento industrial.png" img="img/divisiones/carreras/portada_ing_mantenimiento_Industrial.png" url="http://www.uttab.edu.mx/oferta_educativa/procesos/ingenieria_mantenimiento_industrial.action">
        <informacion_extra><![CDATA[                                        <ul style="list-style-image: url('img/lista.png');">
                        <li><h4>¿Quién es el Ingeniero en Mantenimiento Industrial?</h4>
                            <ul class="list-unstyled">
                                <li>
                                    <p>	Es un profesionista que resuelve problemáticas de la 
										industria en las áreas mecánica, eléctrica, electrónica, 
										neumática, refrigeración, robótica, con 
										conocimientos científicos y tecnológicos para 
										garantizar la confiabilidad de los procesos.
  									</p>
                                </li>
							</ul>
                        </li>
                    </ul>
                    <ul style="list-style-image: url('img/lista.png');">
                        <li><h4>¿Qué aprenderá durante la carrera?</h4>
                            <ul class="list-unstyled">
                                <li> 
									<p>	A mantener en operación constante los equipos  
										aplicando la normatividad en las áreas eléctricas y de
										seguridad e higiene, así como determinar el tipo de 
										mantenimiento tanto preventivo y predictivo 
										aplicable a los equipos, conocimiento en detección 
										de fallas, pruebas destructivas y no destructivas, 
										análisis de vibraciones, entre otras para garantizar la 
										vida útil de los equipos y  optimizar los recursos. 
										También aprenderá a diseñar y elaborar piezas  en 3D,
										programación y construcción de sistemas 
										automatizados y de  robótica. 
									</p>
								</li>
                            </ul>
                        </li>
                    </ul>
                    <ul style="list-style-image: url('img/lista.png');">
                        <li><h4>¿En dónde podrá trabajar?</h4>
                            <ul  class="list-unstyled">
                                <li><p>	En empresas públicas y privadas relacionadas con la 
										industria eléctrica, mecánica, petrolera, automotriz, 
										manufacturera y de servicios.
									</p>
								</li>
                            </ul>
                        </li>
                    </ul> ]]></informacion_extra>
    </carrera>
    <carrera cve_carrera="38" cve_division="13" nombre="TSU en Mantenimiento Área Industrial" continuidad="51"></carrera>
    <carrera cve_carrera="63" cve_division="13" nombre="Ingeniería en Mantenimiento Petrolero" icono="img/movil/android/oferta_educativa/mantenimiento_petrolero.png" img="img/divisiones/carreras/portada_ing_mantenimiento_petrolero.png" url="http://www.uttab.edu.mx/oferta_educativa/procesos/ingenieria_mantenimiento_petrolero.action">
        <informacion_extra><![CDATA[
<ul style="list-style-image: url('http://www.uttab.edu.mx/img/divisiones/carreras/people.png');">
<li><h4>Tener gusto por:</h4>
<ul style="list-style-image: url('img/lista.png');">
<li>Por las matemáticas y física</li>
<li>Investigación e innovación de los equipos mecánicos</li>
<li>Automatización de equipos y procesos</li>
<li>Innovar sistemas productivos</li>
<li>Uso y manejo de maquinaria y equipo</li>
</ul>
</li>
</ul>
<ul style="list-style-image: url('http://www.uttab.edu.mx/img/divisiones/carreras/maletin.png');">
<li><h4>¿Dónde podrá trabajar?</h4>
<ul style="list-style-image: url('img/lista.png');">
<li>Directores y gerentes en construcción, reparación y mantenimiento</li>
<li>Coordinadores y jefes de área en construcción, reparación y mantenimiento</li>
<li>Supervisores de mecánicos y técnicos en mantenimiento y reparación de equipos mecánicos, vehículos de motor, instrumentos industriales y equipo de refrigeración</li>
</ul>
</li>
</ul>
<ul>
<li><h4>¿Qué aprenderá durante la carrera?</h4>
<ul style="list-style-image: url('img/lista.png');">
<li>Diseñar estrategias de mantenimiento para la competitividad de la empresa</li>
<li>Optimizar las actividades de mantenimiento y de operación de los equipos</li>
<li>Diseñar y ejecutar planes y programas de mantenimiento</li>
<li>Integrar proyectos de innovación de los sistemas productivos</li>
<li>Validar estudios de ingeniería que mejoren el mantenimiento de equipos</li>
</ul>
</li>
</ul> 
]]>
        </informacion_extra>
    </carrera>   
    <carrera cve_carrera="55" cve_division="13" nombre="TSU en Mantenimiento Área Petróleo" continuidad="63"></carrera>
    <carrera cve_carrera="59" cve_division="13" nombre="TSU en Energías Renovables Área Calidad y Ahorro de Energía" tipo="2" icono="img/movil/android/oferta_educativa/tsu en energias renovables.png" img="img/divisiones/carreras/portada_tsu_energias_renovables_area_calidad_ahorro_energia.png" url="http://www.uttab.edu.mx/oferta_educativa/procesos/tsu_energias_renovables_area_calidad_ahorro_energia.action">
        <informacion_extra><![CDATA[                                         <ul style="list-style-image: url('img/lista.png');">
                        <li><h4>¿Qué es un TSU en Energías Renovables Área Calidad y Ahorro de Energía?</h4>
                            <ul class="list-unstyled">
                                <li>
                                    <p> Es un profesionista capacitado para controlar 
										procesos de transformación de la materia prima, 
										utilizando métodos químicos y normativos 
										en áreas de la industria alimentaria, química y petrolera.
  									</p>
                                </li>
							</ul>
                        </li>
                    </ul>
                    <ul style="list-style-image: url('img/lista.png');">
                        <li><h4>¿Qué aprenderá durante la carrera?</h4>
                            <ul class="list-unstyled">
                                <li> 
									<p>Diseñar proyectos de energías renovables con base 
									   en un diagnóstico y recursos naturales del entorno 
									   para contribuir al desarrollo sustentable y eficiente 
				                       de energía eléctrica.

									   Evaluar el consumo energético, térmico, eléctrico y 
									   mecánico con base en análisis de información histórica 
									   para conocer las tendencias de consumo y estimar perdidas de energía.

									   Diagnosticar el sistema energético analizando la 
									   generación, distribución y consumo para el uso 
									   racional y eficiente para proponer acciones de eficiencia 
									   energética considerando los estándares aplicables, para 
									   cumplir los requerimientos de la empresa y contribuir a un 
									   desarrollo sustentable.
									</p>
								</li>
                            </ul>
                        </li>
                    </ul>
                    <ul style="list-style-image: url('img/lista.png');">
                        <li><h4>¿En dónde podrá trabajar?</h4>
                            <ul  class="list-unstyled">
                                <li><p>	En empresas públicas y privadas que requieran 
										asistencia en el desarrollo de estrategias 
										relacionadas con el uso eficiente de la energía, al 
										aprovechamiento de energías renovables y proyectos 
										de características sustentables. En el sector industrial 
										que requiera proyectos, estrategias y planes a favor 
										de su economía empresarial. 
									</p>
								</li>
                            </ul>
                        </li>
                    </ul> ]]></informacion_extra>
    </carrera> 
    <carrera cve_carrera="44" cve_division="16" nombre="Ingeniería en Tecnología Ambiental" icono="img/movil/android/oferta_educativa/tecnologia ambiental.png" img="img/divisiones/carreras/portada_ing_tecnología_ambiental.png" url="http://www.uttab.edu.mx/oferta_educativa/quimica/ingenieria_tecnologia_ambiental.action">
        <informacion_extra><![CDATA[                                        <ul style="list-style-image: url('img/lista.png');">
                        <li><h4>¿Quién es el Ingeniero en Tecnología Ambiental?</h4>
                            <ul class="list-unstyled">
                                <li>
                                    <p>	Es un profesionista capacitado con un enfoque 
										de sustentabilidad para solucionar problemas 
										ambientales en suelo, agua y aire; aplicando 
										normas y tecnologías ambientales.</p>
                                </li>
							</ul>
                        </li>
                    </ul>
                    <ul style="list-style-image: url('img/lista.png');">
                        <li><h4>¿Qué aprenderá durante la carrera?</h4>
                            <ul class="list-unstyled">
                                <li> 
									<p>
										A realizar muestreos y análisis de agua, aire y 
										suelo, para la prevención y control de la 
										contaminación, utilizando equipos y/o sistemas 
										de vanguardia, gestionar trámites relacionados
										con la normatividad ambiental ante instancias 
										gubernamentales y a desarrollar programas de 
										seguridad e higiene, así como a operar plantas 
										de tratamiento de aguas.
									</p>
								</li>
                            </ul>
                        </li>
                    </ul>
                    <ul style="list-style-image: url('img/lista.png');">
                        <li><h4>¿En dónde podrá trabajar?</h4>
                            <ul  class="list-unstyled">
                                <li><p>	En las diferentes áreas de empresas públicas 
										o privadas relacionadas con la conservación 
										del ambiente tales como: laboratorios de análisis 
										ambientales, administración ambiental, gestión 
										ambiental, calidad, seguridad e higiene.
									</p>
								</li>
                            </ul>
                        </li>
                    </ul> ]]></informacion_extra>
    </carrera>
    <carrera cve_carrera="48" cve_division="16" nombre="TSU en Química Área Tecnología Ambiental" continuidad="44"></carrera>
    <carrera cve_carrera="45" cve_division="16" nombre="Ingeniería en Química de Procesos Industriales" icono="img/movil/android/oferta_educativa/procesos industriales.png" img="img/divisiones/carreras/portada_ing_quimica_procesos_Industriales.png" url="http://www.uttab.edu.mx/oferta_educativa/quimica/ingenieria_quimica_procesos_industriales.action">
        <informacion_extra><![CDATA[                                         <ul style="list-style-image: url('img/lista.png');">
                        <li><h4>¿Quién es el Ingeniero en Química de Procesos Industriales?</h4>
                            <ul class="list-unstyled">
                                <li>
                                    <p>	Es un profesionista capacitado para controlar procesos 
										de transformación de la materia prima, utilizando métodos químicos 
										y normativos en áreas de la industria alimentaria, química y petrolera.
 									</p>
                                </li>
							</ul>
                        </li>
                    </ul>
                    <ul style="list-style-image: url('img/lista.png');">
                        <li><h4>¿Qué aprenderá durante la carrera?</h4>
                            <ul class="list-unstyled">
                                <li> 
									<p>	Área Prevención de Corrosión y área Química Industrial
										Los principios básicos de química para prevenir la corrosión de 
										materiales metálicos, aplicables en las diferentes industrias; 
										además de métodos de transformación de la materia prima, 
										manejo de equipos para medición y monitoreo de la corrosión 
										y diseño de equipos para la conversión de la materia prima.

										Área Fluidos de Perforación
										A preparar fluidos de perforación y determinar sus 
										propiedades físicas y químicas para optimizar la operación de 
										perforación, además de identificar equipos y herramientas 
										que se utilizan en la perforación de pozos petroleros.
									</p>
								</li>
                            </ul>
                        </li>
                    </ul>
                    <ul style="list-style-image: url('img/lista.png');">
                        <li><h4>¿En dónde podrá trabajar?</h4>
                            <ul  class="list-unstyled">
                                <li><p>	
									Área Prevención de Corrosión, Área Química Industrial y Área Fluidos de Perforación
									En empresas públicas y privadas relacionadas con la industria del petróleo, alimentos 
									y químicos, ya sea en la administración de proyectos, ventas, laboratorios de control 
									de calidad y operación de equipos de transformación de materia prima.
									</p>
								</li>
                            </ul>
                        </li>
                    </ul> ]]></informacion_extra>
    </carrera>
    <carrera cve_carrera="52" cve_division="16" nombre="TSU en Química Área Prevención de Corrosión" continuidad="45"></carrera>
    <carrera cve_carrera="27" cve_division="16" nombre="TSU en Química Área Industrial" continuidad="45"></carrera>
    <carrera cve_carrera="53" cve_division="16" nombre="TSU en Química Área Fluidos de Perforación" continuidad="45"></carrera>    
    <carrera cve_carrera="43" cve_division="15" nombre="Ingeniería en Tecnologías de la Información" icono="img/movil/android/oferta_educativa/tic.png" img="img/divisiones/carreras/portada_ing_tecnologias_informacion.jpg" url="http://www.uttab.edu.mx/oferta_educativa/tic/ingenieria_tecnologias_informacion.action">
        <informacion_extra><![CDATA[                                         <ul style="list-style-image: url('img/lista.png');">
                        <li><h4>¿Quién es el Ingeniero en Tecnologías de la Información?</h4>
                            <ul class="list-unstyled">
                                <li>
                                    <p>	Es un profesionista capacitado para diseñar, 
										administrar, dirigir y evaluar sistemas de 
										tecnologías de la información, que involucre 
										proyectos de instalación de infraestructura y 
										desarrollo de sistemas informáticos.
 									</p>
                                </li>
							</ul>
                        </li>
                    </ul>
                    <ul style="list-style-image: url('img/lista.png');">
                        <li><h4>¿Qué aprenderá durante la carrera?</h4>
                            <ul class="list-unstyled">
                                <li> 
									<p>	A instalar y configurar equipos de redes y 
										telecomunicaciones, desarrollar sistemas de 
										información, diseño y elaboración de páginas 
										web, administrar y dar mantenimiento a 
										infraestructuras de telecomunicaciones.
									</p>
								</li>
                            </ul>
                        </li>
                    </ul>
                    <ul style="list-style-image: url('img/lista.png');">
                        <li><h4>¿En dónde podrá trabajar?</h4>
                            <ul  class="list-unstyled">
                                <li><p>	En empresas públicas o privadas que requieran o 
										utilicen infraestructura de telecomunicaciones, 
										en áreas administrativas, mantenimiento y desarrollo 
										de nuevos sistemas de información o 
										creando su propia empresa de servicios.
									</p>
								</li>
                            </ul>
                        </li>
                    </ul> ]]></informacion_extra>
    </carrera>
    <carrera cve_carrera="60" cve_division="15" nombre="TSU en Tecnologías de la Información y Comunicación Área Multimedia y Comercio Electrónico" continuidad="43"></carrera>
    <carrera cve_carrera="31" cve_division="15" nombre="TSU en Tecnologías de la Información y Comunicación Área Redes y Telecomunicaciones" continuidad="43"></carrera>
    <carrera cve_carrera="35" cve_division="15" nombre="TSU en Tecnologías de la Información y Comunicación Área Sistemas Informáticos" continuidad="43"></carrera>
    <carrera cve_carrera="56" cve_division="17" nombre="Licenciatura en Gastronomía" icono="img/movil/android/oferta_educativa/gastronimia.png" img="img/divisiones/carreras/portada_lic_gastronomia.png" url="http://www.uttab.edu.mx/oferta_educativa/turismo/licenciatura_gastronomia.action">
        <informacion_extra><![CDATA[                                        <ul style="list-style-image: url('img/lista.png');">
                        <li><h4>¿Quién es el Licenciado en Gastronomía?</h4>
                            <ul class="list-unstyled">
                                <li>
                                    <p>	Es un profesionista capacitado para administrar 
										establecimientos de alimentos y bebidas, 
										empleando las técnicas del arte culinario acordes
										a las tendencias gastronómicas, así como a la 
										evolución de la gastronomía.
									</p>
                                </li>
							</ul>
                        </li>
                    </ul>
                    <ul style="list-style-image: url('img/lista.png');">
                        <li><h4>¿Qué aprenderá durante la carrera?</h4>
                            <ul class="list-unstyled">
                                <li> 
									<p>	Técnicas de cocción, montajes y estandarización 
										de platillos, producción de alimentos a gran 
										escala, logística de eventos gastronómicos, 
										servicios de alimentos y bebidas, catas de vino, 
										maridaje, repostería, cocina internacional, diseño
										de menús, diseño de cocina y manejo higiénico 
										de los alimentos.
									</p>
								</li>
                            </ul>
                        </li>
                    </ul>
                    <ul style="list-style-image: url('img/lista.png');">
                        <li><h4>¿En dónde podrá trabajar?</h4>
                            <ul  class="list-unstyled">
                                <li><p>	En hospitales, hoteles, restaurantes, cruceros, 
										comedores industriales, comedores escolares, 
										supermercados, panaderías, pastelerías, 
										realizando consultorías, como chef instructor o 
										creando su propia empresa.
									</p>
								</li>
                            </ul>
                        </li>
                    </ul> ]]></informacion_extra>
    </carrera>
    <carrera cve_carrera="49" cve_division="17" nombre="TSU en Gastronomía" continuidad="56"></carrera>
    <carrera cve_carrera="46" cve_division="17" nombre="Licenciatura en Gestión y Desarrollo Turístico" icono="img/movil/android/oferta_educativa/desarollo turistico.png" img="img/divisiones/carreras/portada_lic_gestion_desarrollo_turistico.png" url="http://www.uttab.edu.mx/oferta_educativa/turismo/licenciatura_gestion_desarrollo_turistico.action">
        <informacion_extra><![CDATA[                                        <ul style="list-style-image: url('img/lista.png');">
                        <li><h4>¿Quién es el Licenciado en Gestión y Desarrollo Turístico?</h4>
                            <ul class="list-unstyled">
                                <li>
                                    <p>	Es un profesionista capacitado con visión competitiva 
										dentro del mundo globalizado para administrar, 
										desarrollar, dirigir y ejecutar acciones en empresas 
										prestadoras de servicios turísticos.
 									</p>
                                </li>
							</ul>
                        </li>
                    </ul>
                    <ul style="list-style-image: url('img/lista.png');">
                        <li><h4>¿Qué aprenderá durante la carrera?</h4>
                            <ul class="list-unstyled">
                                <li> 
									<p>	A desarrollar áreas con potencial turístico, protocolo de 
										intercambios internacionales, manejo de personal, 
										itinerarios de viaje, establecer sistemas de calidad, 
										organización de congresos y convenciones, dominio del 
										idioma extranjero, patrimonio turístico nacional e 
										internacional, desarrollar paquetes turísticos nacionales e 
										internacionales, protocolo de etiqueta y servicios.
									</p>
								</li>
                            </ul>
                        </li>
                    </ul>
                    <ul style="list-style-image: url('img/lista.png');">
                        <li><h4>¿En dónde podrá trabajar?</h4>
                            <ul  class="list-unstyled">
                                <li><p>	En empresas privadas y públicas en el ramo de la 
										hotelería, aeropuertos, líneas de transportación 
										terrestres, aéreas, acuáticas, áreas naturales 
										protegidas, zonas arqueológicas, restaurantes, 
										agencias de viajes, bares, organización de eventos 
										sociales, embajadas, consulados, consultoría, 
										capacitación turística y cruceros.
									</p>
								</li>
                            </ul>
                        </li>
                    </ul> ]]></informacion_extra>
    </carrera>
    <carrera cve_carrera="54" cve_division="17" nombre="TSU en Turismo Área Hotelería" continuidad="46"></carrera>  
</carreras>